cyberfusion/BorgSupport/__init__.py
cyberfusion/BorgSupport/archives.py
cyberfusion/BorgSupport/borg_cli.py
cyberfusion/BorgSupport/operations.py
cyberfusion/BorgSupport/repositories.py
cyberfusion/BorgSupport/utilities.py
cyberfusion/BorgSupport/exceptions/__init__.py
python3_cyberfusion_borg_support-1.6.dist-info/METADATA
python3_cyberfusion_borg_support-1.6.dist-info/WHEEL
python3_cyberfusion_borg_support-1.6.dist-info/top_level.txt
python3_cyberfusion_borg_support-1.6.dist-info/RECORD
