Metadata-Version: 2.4
Name: python3-cyberfusion-borg-support
Version: 1.6
Summary: Library for Borg.
Author-email: Cyberfusion <support@cyberfusion.io>
Project-URL: Source, https://github.com/CyberfusionIO/python3-cyberfusion-borg-support
